django_testing_utils/__init__.py
django_testing_utils/mixins.py
django_testing_utils/py.typed
django_testing_utils/utils.py
django_testing_utils-0.8.0.dist-info/licenses/LICENSE
django_testing_utils-0.8.0.dist-info/METADATA
django_testing_utils-0.8.0.dist-info/WHEEL
django_testing_utils-0.8.0.dist-info/top_level.txt
django_testing_utils-0.8.0.dist-info/RECORD
